indexpaper/__init__.py
indexpaper/check_scholar.py
indexpaper/evaluate.py
indexpaper/index.py
indexpaper/indexing.py
indexpaper/paperset.py
indexpaper/resolvers.py
indexpaper/search.py
indexpaper/splitting.py
indexpaper/utils.py
indexpaper-0.0.23.dist-info/LICENSE
indexpaper-0.0.23.dist-info/METADATA
indexpaper-0.0.23.dist-info/WHEEL
indexpaper-0.0.23.dist-info/entry_points.txt
indexpaper-0.0.23.dist-info/top_level.txt
indexpaper-0.0.23.dist-info/RECORD
