Metadata-Version: 2.1
Name: indexpaper
Version: 0.0.23
Summary: indexpaper - library to index papers with vector databases
Author: antonkulaga (Anton Kulaga)
Author-email: <antonkulaga@gmail.com>
Keywords: python,utils,files,papers,download,index,vector databases
Classifier: Development Status :: 2 - Pre-Alpha
Classifier: Intended Audience :: Developers
Classifier: Programming Language :: Python :: 3.10
Classifier: Programming Language :: Python :: 3.11
Classifier: Operating System :: Unix
Classifier: Operating System :: MacOS :: MacOS X
Classifier: Operating System :: Microsoft :: Windows
License-File: LICENSE
Requires-Dist: pycomfort >=0.0.15
Requires-Dist: hybrid-search >=0.0.12
Requires-Dist: more-itertools
Requires-Dist: click
Requires-Dist: python-dotenv
Requires-Dist: tiktoken
Requires-Dist: FlagEmbedding >=1.2.8
Requires-Dist: langchain >=0.1.12
Requires-Dist: langchain-community >=0.0.28
Requires-Dist: openai
Requires-Dist: Deprecated
Requires-Dist: loguru
Requires-Dist: qdrant-client >=1.8.0
Requires-Dist: sentence-transformers
Requires-Dist: datasets
Requires-Dist: polars >=0.20.14
Requires-Dist: beartype
